pepr/__init__.py
pepr/attack.py
pepr/attack_runner.py
pepr/report.py
pepr/utilities.py
pepr/privacy/__init__.py
pepr/privacy/art_extraction_wrapper.py
pepr/privacy/art_inference_wrapper.py
pepr/privacy/gmia.py
pepr/privacy/mia.py
pepr/robustness/__init__.py
pepr/robustness/art_wrapper.py
pepr/robustness/foolbox_wrapper.py
tests/integration/__init__.py
tests/integration/test_gmia_fashion_mnist.py
tests/unit/__init__.py
tests/unit/test_pepr_privacy_gmia.py
tests/unit/test_pepr_privacy_mia.py
mlpepr-0.1b6.dist-info/LICENSE
mlpepr-0.1b6.dist-info/METADATA
mlpepr-0.1b6.dist-info/WHEEL
mlpepr-0.1b6.dist-info/top_level.txt
mlpepr-0.1b6.dist-info/RECORD
